Flask_Bootstrap4-4.0.1.dist-info/DESCRIPTION.rst
Flask_Bootstrap4-4.0.1.dist-info/METADATA
Flask_Bootstrap4-4.0.1.dist-info/RECORD
Flask_Bootstrap4-4.0.1.dist-info/WHEEL
Flask_Bootstrap4-4.0.1.dist-info/metadata.json
Flask_Bootstrap4-4.0.1.dist-info/top_level.txt
flask_bootstrap/__init__.py
flask_bootstrap/forms.py
flask_bootstrap/nav.py
flask_bootstrap/static/jquery.js
flask_bootstrap/static/jquery.min.js
flask_bootstrap/static/jquery.min.map
flask_bootstrap/static/css/bootstrap-grid.css
flask_bootstrap/static/css/bootstrap-grid.css.map
flask_bootstrap/static/css/bootstrap-grid.min.css
flask_bootstrap/static/css/bootstrap-grid.min.css.map
flask_bootstrap/static/css/bootstrap-reboot.css
flask_bootstrap/static/css/bootstrap-reboot.css.map
flask_bootstrap/static/css/bootstrap-reboot.min.css
flask_bootstrap/static/css/bootstrap-reboot.min.css.map
flask_bootstrap/static/css/bootstrap.css
flask_bootstrap/static/css/bootstrap.css.map
flask_bootstrap/static/css/bootstrap.min.css
flask_bootstrap/static/css/bootstrap.min.css.map
flask_bootstrap/static/js/bootstrap.bundle.js
flask_bootstrap/static/js/bootstrap.bundle.js.map
flask_bootstrap/static/js/bootstrap.bundle.min.js
flask_bootstrap/static/js/bootstrap.bundle.min.js.map
flask_bootstrap/static/js/bootstrap.js
flask_bootstrap/static/js/bootstrap.js.map
flask_bootstrap/static/js/bootstrap.min.js
flask_bootstrap/static/js/bootstrap.min.js.map
flask_bootstrap/static/umd/popper.js
flask_bootstrap/static/umd/popper.js.map
flask_bootstrap/static/umd/popper.min.js
flask_bootstrap/static/umd/popper.min.js.map
flask_bootstrap/templates/bootstrap/base.html
flask_bootstrap/templates/bootstrap/google.html
flask_bootstrap/templates/bootstrap/pagination.html
flask_bootstrap/templates/bootstrap/utils.html
flask_bootstrap/templates/bootstrap/wtf.html
